rivertext/__init__.py
rivertext/_version.py
rivertext/evaluator/__init__.py
rivertext/evaluator/eval.py
rivertext/models/__init__.py
rivertext/models/iw2v.py
rivertext/models/wcm.py
rivertext/models/base/__init__.py
rivertext/models/base/iwv.py
rivertext/models/iword2vec/__init__.py
rivertext/models/iword2vec/model.py
rivertext/models/iword2vec/preprocessing.py
rivertext/models/iword2vec/unigram_table.py
rivertext/utils/__init__.py
rivertext/utils/data.py
rivertext/utils/rand.py
rivertext/utils/vocab.py
tests/__init__.py
tests/models/__init__.py
tests/models/test_iw2v.py
tests/models/test_iwcm.py
tests/models/test_unigram_table.py
tests/utils/__init__.py
tests/utils/test_data.py
tests/utils/test_rand.py
tests/utils/test_vocab.py
rivertext-0.0.2.dist-info/LICENSE
rivertext-0.0.2.dist-info/METADATA
rivertext-0.0.2.dist-info/WHEEL
rivertext-0.0.2.dist-info/top_level.txt
rivertext-0.0.2.dist-info/RECORD
