Metadata-Version: 2.1
Name: rivertext
Version: 0.0.2
Summary: An Python Library for training and evaluating on Incremental Word Embedding.
Home-page: https://github.com/dccuchile/rivertext
Download-URL: https://github.com/dccuchile/rivertext
Author: Rivertext Team
Maintainer: Rivertext Team
Maintainer-email: gabrielturrab@ug.uchile.cl
License: new BSD
Classifier: Intended Audience :: Science/Research
Classifier: Intended Audience :: Developers
Classifier: License :: OSI Approved
Classifier: Programming Language :: Python
Classifier: Topic :: Software Development
Classifier: Topic :: Scientific/Engineering
Classifier: Operating System :: Microsoft :: Windows
Classifier: Operating System :: POSIX
Classifier: Operating System :: Unix
Classifier: Operating System :: MacOS
Classifier: Programming Language :: Python :: 3.6
Classifier: Programming Language :: Python :: 3.7
Classifier: Programming Language :: Python :: 3.8
Classifier: Programming Language :: Python :: 3.9
Classifier: Programming Language :: Python :: 3.10
Requires-Python: >=3.6
License-File: LICENSE
Requires-Dist: nltk
Requires-Dist: numpy
Requires-Dist: river
Requires-Dist: scikit-learn
Requires-Dist: scipy
Requires-Dist: torch
Requires-Dist: tqdm
Requires-Dist: word-embeddings-benchmarks
